{
	"name": "DS_getmetadata",
	"properties": {
		"linkedServiceName": {
			"referenceName": "LS_getmetadata",
			"type": "LinkedServiceReference"
		},
		"annotations": [],
		"type": "DelimitedText",
		"typeProperties": {
			"location": {
				"type": "AzureBlobFSLocation",
				"folderPath": "getmetadatasrc",
				"fileSystem": "adlscont"
			},
			"columnDelimiter": ",",
			"escapeChar": "\\",
			"firstRowAsHeader": true,
			"quoteChar": "\""
		},
		"schema": [
			{
				"name": "pid",
				"type": "String"
			},
			{
				"name": "pname",
				"type": "String"
			},
			{
				"name": "price",
				"type": "String"
			}
		]
	},
	"type": "Microsoft.DataFactory/factories/datasets"
}